MANIFEST.in
README.md
requirements.txt
setup.py
keras_transformer_xl/__init__.py
keras_transformer_xl/loader.py
keras_transformer_xl/memory.py
keras_transformer_xl/pos_embed.py
keras_transformer_xl/rel_bias.py
keras_transformer_xl/rel_multi_head.py
keras_transformer_xl/scale.py
keras_transformer_xl/sequence.py
keras_transformer_xl/transformer_xl.py
keras_transformer_xl.egg-info/PKG-INFO
keras_transformer_xl.egg-info/SOURCES.txt
keras_transformer_xl.egg-info/dependency_links.txt
keras_transformer_xl.egg-info/requires.txt
keras_transformer_xl.egg-info/top_level.txt
tests/__init__.py
tests/test_loader.py
tests/test_memory.py
tests/test_pos_embed.py
tests/test_rel_multi_head.py
tests/test_sequence.py
tests/test_transformer_xl.py