Metadata-Version: 2.1
Name: keras-transformer-xl
Version: 0.14.0
Summary: Transformer-XL implemented in Keras
Home-page: https://github.com/CyberZHG/keras-transformer-xl
Author: CyberZHG
Author-email: CyberZHG@users.noreply.github.com
License: MIT
Platform: UNKNOWN
Classifier: Programming Language :: Python :: 3
Classifier: License :: OSI Approved :: MIT License
Classifier: Operating System :: OS Independent
